multilectic/__init__.py
multilectic/positions.py
multilectic-0.0.8.dist-info/LICENSE
multilectic-0.0.8.dist-info/METADATA
multilectic-0.0.8.dist-info/WHEEL
multilectic-0.0.8.dist-info/top_level.txt
multilectic-0.0.8.dist-info/RECORD
