Metadata-Version: 2.1
Name: multilectic
Version: 0.0.8
Summary: The multilogue philosophy with more than two 'truths'
Author-email: Alexander Fedotov <alex.fedotov@aol.com>
Project-URL: Homepage, https://github.com/multilectic/multilectic
Project-URL: Bug Tracker, https://github.com/multilectic/multilectic/issues
Classifier: Programming Language :: Python :: 3
Classifier: License :: OSI Approved :: MIT License
Classifier: Operating System :: OS Independent
Requires-Python: >=3.10
License-File: LICENSE
